tap_paylocity/__init__.py
tap_paylocity/__main__.py
tap_paylocity/auth.py
tap_paylocity/client.py
tap_paylocity/schemas/__init__.py
tap_paylocity/streams.py
tap_paylocity/tap.py
tap_paylocity-1.2.2.dist-info/LICENSE
tap_paylocity-1.2.2.dist-info/METADATA
tap_paylocity-1.2.2.dist-info/WHEEL
tap_paylocity-1.2.2.dist-info/entry_points.txt
tap_paylocity-1.2.2.dist-info/RECORD
