Metadata-Version: 2.3
Name: tap-paylocity
Version: 1.2.2
Summary: Singer tap for Paylocity, built with the Meltano Singer SDK.
License: Apache-2.0
Keywords: ELT,Paylocity
Author: Derek Wayne
Author-email: derek@getrapidinsights.com
Requires-Python: >=3.9
Classifier: Intended Audience :: Developers
Classifier: License :: OSI Approved :: Apache Software License
Classifier: Operating System :: OS Independent
Classifier: Programming Language :: Python :: 3
Classifier: Programming Language :: Python :: 3.9
Classifier: Programming Language :: Python :: 3.10
Classifier: Programming Language :: Python :: 3.11
Classifier: Programming Language :: Python :: 3.12
Classifier: Programming Language :: Python :: 3.13
Provides-Extra: s3
Requires-Dist: fs-s3fs (>=1.1.1,<1.2.0) ; extra == "s3"
Requires-Dist: requests (>=2.32.3,<2.33.0)
Requires-Dist: singer-sdk (>=0.43.1,<0.44.0)
